app/__init__.py
app/app.py
app/change_processor.py
app/context_storage.py
app/file_indexer.py
app/llm_client.py
app/settings.py
app/shared.py
coda_ai_assistant-0.1.dist-info/METADATA
coda_ai_assistant-0.1.dist-info/WHEEL
coda_ai_assistant-0.1.dist-info/entry_points.txt
coda_ai_assistant-0.1.dist-info/RECORD
