Metadata-Version: 2.1
Name: coda-ai-assistant
Version: 0.1
Summary: A general-purpose AI coding assistant
Home-page: https://github.com/vtsaplin/coda
License: MIT
Keywords: AI,coding assistant,automation
Author: Vitaly Tsaplin
Requires-Python: >=3.10,<4.0
Classifier: License :: OSI Approved :: MIT License
Classifier: Operating System :: OS Independent
Classifier: Programming Language :: Python :: 3
Classifier: Programming Language :: Python :: 3.10
Classifier: Programming Language :: Python :: 3.11
Classifier: Programming Language :: Python :: 3.12
Classifier: Programming Language :: Python :: 3.13
Requires-Dist: InquirerPy
Requires-Dist: backoff
Requires-Dist: chromadb
Requires-Dist: colorama
Requires-Dist: humps
Requires-Dist: jsonschema
Requires-Dist: langchain
Requires-Dist: langchain-openai
Requires-Dist: openai
Requires-Dist: pathspec
Requires-Dist: pygments
Requires-Dist: python-dotenv
Requires-Dist: requests
Requires-Dist: requests_toolbelt
Requires-Dist: tornado
Requires-Dist: tqdm
Requires-Dist: unidiff
Project-URL: Repository, https://github.com/vtsaplin/coda
